README.md
setup.cfg
setup.py
hgP/__init__.py
hgP/geoprocessing.py
hgP.egg-info/PKG-INFO
hgP.egg-info/SOURCES.txt
hgP.egg-info/dependency_links.txt
hgP.egg-info/requires.txt
hgP.egg-info/top_level.txt